opentraining/__init__.py
opentraining/core/element.py
opentraining/core/errors.py
opentraining/core/exercise.py
opentraining/core/group.py
opentraining/core/node.py
opentraining/core/person.py
opentraining/core/project.py
opentraining/core/soup.py
opentraining/core/task.py
opentraining/core/topic.py
opentraining/sphinxglue/__init__.py
opentraining/sphinxglue/dia.py
opentraining/sphinxglue/errors.py
opentraining/sphinxglue/exercise.py
opentraining/sphinxglue/graph.py
opentraining/sphinxglue/group.py
opentraining/sphinxglue/grouplist.py
opentraining/sphinxglue/person.py
opentraining/sphinxglue/personstats.py
opentraining/sphinxglue/project.py
opentraining/sphinxglue/project_personstats.py
opentraining/sphinxglue/project_taskstats.py
opentraining/sphinxglue/soup.py
opentraining/sphinxglue/task.py
opentraining/sphinxglue/taskstats.py
opentraining/sphinxglue/topic.py
opentraining/sphinxglue/utils.py
opentraining-0.8.6.dist-info/LICENSE
opentraining-0.8.6.dist-info/METADATA
opentraining-0.8.6.dist-info/WHEEL
opentraining-0.8.6.dist-info/top_level.txt
opentraining-0.8.6.dist-info/RECORD
